{
  "slug": "digimon-story-time-stranger",
  "updatedAt": "2026-07-14T04:18:31.797Z",
  "name": "Digimon Story Time Stranger",
  "headerImage": "https://shared.akamai.steamstatic.com/store_item_assets/steam/apps/1984270/e3f14e956b8e6ee96c257b38e82241cd1522bc80/header_alt_assets_1.jpg?t=1783997411",
  "genres": [
    "RPG"
  ],
  "releaseDate": "Oct 2, 2025",
  "comingSoon": false,
  "metacritic": null,
  "recommendations": 15297,
  "reviewDesc": "Very Positive",
  "reviewCount": 21798,
  "reviewPercent": 90
}
