{
  "updatedAt": "2026-07-18T09:12:36.687Z",
  "sources": {
    "steam-regional": {
      "lastAttemptAt": "2026-07-18T09:09:59.664Z",
      "lastSuccessAt": "2026-07-18T09:09:59.664Z",
      "consecutiveFailures": 0,
      "note": "changed 1, unchanged 90, skipped 0, failed region requests 0, expected 91"
    },
    "eshop-regional": {
      "lastAttemptAt": "2026-07-18T09:11:14.961Z",
      "lastSuccessAt": "2026-07-18T09:11:14.961Z",
      "consecutiveFailures": 0,
      "note": "changed 0, unchanged 97, skipped 0, failed region requests 0, expected 97"
    },
    "xbox-us": {
      "lastAttemptAt": "2026-07-13T12:07:55.170Z",
      "lastSuccessAt": "2026-07-13T12:07:55.170Z",
      "consecutiveFailures": 0,
      "note": "changed 0, unchanged 14, failed products 0, failed requests 0, expected 14"
    },
    "steam-offers": {
      "lastAttemptAt": "2026-07-15T06:02:09.176Z",
      "lastSuccessAt": "2026-07-15T06:02:09.176Z",
      "consecutiveFailures": 0,
      "note": "changed 0, unchanged 9, files written 0, failed requests 0, expected 9"
    },
    "meta": {
      "lastAttemptAt": "2026-07-16T15:57:35.996Z",
      "lastSuccessAt": "2026-07-16T15:57:35.996Z",
      "consecutiveFailures": 0,
      "note": "changed 90, unchanged 41, failed games 0, expected 131"
    },
    "meta:shard-0": {
      "lastAttemptAt": "2026-07-17T09:30:36.453Z",
      "lastSuccessAt": "2026-07-17T09:30:36.453Z",
      "consecutiveFailures": 0,
      "note": "changed 7, unchanged 0, failed games 0, expected 7"
    },
    "meta:shard-1": {
      "lastAttemptAt": "2026-07-18T09:12:36.687Z",
      "lastSuccessAt": "2026-07-18T09:12:36.687Z",
      "consecutiveFailures": 0,
      "note": "changed 19, unchanged 0, failed games 0, expected 19"
    },
    "meta:shard-2": {
      "lastAttemptAt": "2026-07-16T15:57:35.997Z",
      "lastSuccessAt": "2026-07-16T15:57:35.997Z",
      "consecutiveFailures": 0,
      "note": "changed 90, unchanged 41, failed games 0, expected 131"
    },
    "meta:shard-3": {
      "lastAttemptAt": "2026-07-16T15:57:35.997Z",
      "lastSuccessAt": "2026-07-16T15:57:35.997Z",
      "consecutiveFailures": 0,
      "note": "changed 90, unchanged 41, failed games 0, expected 131"
    },
    "meta:shard-4": {
      "lastAttemptAt": "2026-07-16T15:57:35.998Z",
      "lastSuccessAt": "2026-07-16T15:57:35.998Z",
      "consecutiveFailures": 0,
      "note": "changed 90, unchanged 41, failed games 0, expected 131"
    },
    "meta:shard-5": {
      "lastAttemptAt": "2026-07-16T15:57:35.998Z",
      "lastSuccessAt": "2026-07-16T15:57:35.998Z",
      "consecutiveFailures": 0,
      "note": "changed 90, unchanged 41, failed games 0, expected 131"
    },
    "meta:shard-6": {
      "lastAttemptAt": "2026-07-16T15:57:35.998Z",
      "lastSuccessAt": "2026-07-16T15:57:35.998Z",
      "consecutiveFailures": 0,
      "note": "changed 90, unchanged 41, failed games 0, expected 131"
    },
    "meta:shard-7": {
      "lastAttemptAt": "2026-07-16T15:57:35.998Z",
      "lastSuccessAt": "2026-07-16T15:57:35.998Z",
      "consecutiveFailures": 0,
      "note": "changed 90, unchanged 41, failed games 0, expected 131"
    },
    "meta:shard-8": {
      "lastAttemptAt": "2026-07-16T15:57:35.999Z",
      "lastSuccessAt": "2026-07-16T15:57:35.999Z",
      "consecutiveFailures": 0,
      "note": "changed 90, unchanged 41, failed games 0, expected 131"
    },
    "meta:shard-9": {
      "lastAttemptAt": "2026-07-16T15:57:36.000Z",
      "lastSuccessAt": "2026-07-16T15:57:36.000Z",
      "consecutiveFailures": 0,
      "note": "changed 90, unchanged 41, failed games 0, expected 131"
    },
    "meta:shard-10": {
      "lastAttemptAt": "2026-07-16T15:57:36.000Z",
      "lastSuccessAt": "2026-07-16T15:57:36.000Z",
      "consecutiveFailures": 0,
      "note": "changed 90, unchanged 41, failed games 0, expected 131"
    },
    "meta:shard-11": {
      "lastAttemptAt": "2026-07-16T15:57:36.000Z",
      "lastSuccessAt": "2026-07-16T15:57:36.000Z",
      "consecutiveFailures": 0,
      "note": "changed 90, unchanged 41, failed games 0, expected 131"
    },
    "meta:shard-12": {
      "lastAttemptAt": "2026-07-16T15:57:36.000Z",
      "lastSuccessAt": "2026-07-16T15:57:36.000Z",
      "consecutiveFailures": 0,
      "note": "changed 90, unchanged 41, failed games 0, expected 131"
    },
    "meta:shard-13": {
      "lastAttemptAt": "2026-07-16T15:57:36.001Z",
      "lastSuccessAt": "2026-07-16T15:57:36.001Z",
      "consecutiveFailures": 0,
      "note": "changed 90, unchanged 41, failed games 0, expected 131"
    },
    "steam-regional:extended-2": {
      "lastAttemptAt": "2026-07-17T09:29:03.486Z",
      "lastSuccessAt": "2026-07-17T09:29:03.486Z",
      "consecutiveFailures": 0,
      "note": "changed 0, unchanged 1, skipped 0, failed region requests 0, expected 1"
    },
    "steam-regional:extended-0": {
      "lastAttemptAt": "2026-07-18T09:10:30.485Z",
      "lastSuccessAt": "2026-07-18T09:10:30.485Z",
      "consecutiveFailures": 0,
      "note": "changed 0, unchanged 17, skipped 0, failed region requests 0, expected 17"
    }
  }
}
